cquest_secret_manager/__init__.py
cquest_secret_manager/program/__init__.py
cquest_secret_manager/program/cquest_secret_manager_functions.py
cquest_secret_manager/program/runner_secret_manager.py
cquest_secret_manager-0.3.0.dist-info/LICENSE
cquest_secret_manager-0.3.0.dist-info/METADATA
cquest_secret_manager-0.3.0.dist-info/WHEEL
cquest_secret_manager-0.3.0.dist-info/top_level.txt
cquest_secret_manager-0.3.0.dist-info/RECORD
