Metadata-Version: 2.1
Name: cquest-secret-manager
Version: 0.3.0
Summary: python implementation of the functionalities of secret manager
Home-page: http://gitlab.com/cquest1/cquest_secret_manager
Author: Ksenija Babarokina
Author-email: ksenija.b@cquest.ai
License: UNKNOWN
Keywords: cquest_secret_manager
Platform: UNKNOWN
Classifier: Programming Language :: Python :: 3
Classifier: License :: OSI Approved :: MIT License
Classifier: Operating System :: OS Independent
Requires-Python: >=3.6
Requires-Dist: coverage (~=5.3)
Requires-Dist: flake8 (~=3.8.4)
Requires-Dist: google (~=3.0.0)
Requires-Dist: google-cloud-secret-manager (~=2.0.0)
Requires-Dist: google-cloud-storage (~=1.35.0)
Requires-Dist: loguru (~=0.5.3)
Requires-Dist: mypy (~=0.790)
Requires-Dist: pylint (~=2.6)
Requires-Dist: pytest (~=6.1.1)
Requires-Dist: pytest-cov (~=2.10)
Requires-Dist: pyyaml (~=5.3.1)
Requires-Dist: setuptools (~=49.6.0)
